{"data":{"user":{"name":"Divesh Thakker","bio":"Google DSC Lead @ KJSCE | Full Stack Developer | Machine Learning Enthusiast | LeetCoder | Pre-final year CSE","isHireable":false,"avatarUrl":"https://avatars.githubusercontent.com/u/52334437?u=edd8e41b8f86cc45e47a547915d3653f28f2dea6&v=4","location":"Mumbai, Maharashtra","pinnedItems":{"totalCount":6,"edges":[{"node":{"name":"Co_Vaccine","description":"Co-Vaccine provides a digital medium for citizens of India to book appointments for vaccination. It is a portal which helps people locate the nearest vaccine center, find directions to it, and help the user to book an appointment, along with notifications.","forkCount":0,"stargazers":{"totalCount":0},"url":"https://github.com/Divesh2201/Co_Vaccine","id":"MDEwOlJlcG9zaXRvcnkzNDMzNzU0NDE=","diskUsage":49214,"primaryLanguage":{"name":"Python","color":"#3572A5"}}},{"node":{"name":"Plant-Pathology-Prediction","description":null,"forkCount":1,"stargazers":{"totalCount":0},"url":"https://github.com/Divesh2201/Plant-Pathology-Prediction","id":"MDEwOlJlcG9zaXRvcnk0MDAxNDA0NDM=","diskUsage":74634,"primaryLanguage":{"name":"Jupyter Notebook","color":"#DA5B0B"}}},{"node":{"name":"Mumbai_Police","description":null,"forkCount":0,"stargazers":{"totalCount":0},"url":"https://github.com/Divesh2201/Mumbai_Police","id":"MDEwOlJlcG9zaXRvcnkzNDY3ODA0NTM=","diskUsage":62859,"primaryLanguage":{"name":"Python","color":"#3572A5"}}},{"node":{"name":"github-commands-cheatsheet","description":"All necessary Git command's complete cheatsheet! ","forkCount":8,"stargazers":{"totalCount":6},"url":"https://github.com/Divesh2201/github-commands-cheatsheet","id":"MDEwOlJlcG9zaXRvcnkzNTE3ODU3NTM=","diskUsage":14,"primaryLanguage":null}},{"node":{"name":"netflix","description":"Netflix Clone using Advance React and Firebase.","forkCount":1,"stargazers":{"totalCount":1},"url":"https://github.com/Divesh2201/netflix","id":"MDEwOlJlcG9zaXRvcnkzNDYxNTQxNTI=","diskUsage":24831,"primaryLanguage":{"name":"JavaScript","color":"#f1e05a"}}},{"node":{"name":"crime-management-webapp","description":"Developed using Spring Boot and Spring Security, this application transforms the Legal System onto a digital platform. It includes role based authentication, allowing the users to securely file complaints. Also, admin can verify and update the status of the complaints. ","forkCount":2,"stargazers":{"totalCount":0},"url":"https://github.com/Divesh2201/crime-management-webapp","id":"MDEwOlJlcG9zaXRvcnkyOTkzMTc4ODc=","diskUsage":118,"primaryLanguage":{"name":"Java","color":"#b07219"}}}]}}}}